{
  "cli": {
    "version": ">= 16.0.0"
  },
  "build": {
    "development": {
      "developmentClient": true,
      "distribution": "internal",
      "env": {
        "EXPO_PUBLIC_API_URL": "http://localhost:8080"
      }
    },
    "preview": {
      "distribution": "internal",
      "android": {
        "buildType": "apk"
      },
      "env": {
        "EXPO_PUBLIC_API_URL": "https://square-up-api.fly.dev"
      }
    },
    "production": {
      "autoIncrement": true,
      "env": {
        "EXPO_PUBLIC_API_URL": "https://square-up-api.fly.dev"
      }
    }
  },
  "submit": {
    "production": {}
  }
}
